seldonian/__init__.py
seldonian/algorithm.py
seldonian/bounds.py
seldonian/cmaes.py
seldonian/examples.py
seldonian/objectives.py
seldonian/parser.py
seldonian/seldonian.py
seldonian/synthetic.py
seldonian/utils.py
seldonian-0.0.3.dev0.dist-info/METADATA
seldonian-0.0.3.dev0.dist-info/WHEEL
seldonian-0.0.3.dev0.dist-info/top_level.txt
seldonian-0.0.3.dev0.dist-info/RECORD
