Metadata-Version: 2.1
Name: seldonian
Version: 0.0.3.dev0
Summary: Train model with safety constraints
Home-page: https://abdulhannan.in/seldonian-fairness
Author: Abdul Hannan Kanji
Author-email: kanji@adulhannan.in
License: MIT
Platform: UNKNOWN
Requires-Python: >3.5
Requires-Dist: numpy (>=1.19.2)
Requires-Dist: scikit-learn (==0.23.2)
Requires-Dist: scipy (==1.5.3)
Requires-Dist: numba (==0.51.2)
Requires-Dist: torch (==1.6.0)
Requires-Dist: pandas (==1.1.3)
